kubesh/__init__.py
kubesh/__main__.py
kubesh/_version.py
kubesh/api.py
kubesh/cli.py
kubesh/cmd_handler.py
kubesh/mapper.py
kubesh/plugins.py
kubesh/test_version.py
kubesh/commands/__init__.py
kubesh/commands/help.py
kubesh/commands/namespaces.py
kubesh/commands/nodes.py
kubesh/commands/quit.py
kubesh/consoles/__init__.py
kubesh/consoles/stdin.py
kubesh/consoles/terminal.py
kubesh-0.0.4.dist-info/LICENSE
kubesh-0.0.4.dist-info/METADATA
kubesh-0.0.4.dist-info/WHEEL
kubesh-0.0.4.dist-info/entry_points.txt
kubesh-0.0.4.dist-info/top_level.txt
kubesh-0.0.4.dist-info/RECORD
