Metadata-Version: 2.1
Name: kubesh
Version: 0.0.4
Summary: A kubernetes shell
Home-page: https://github.com/joaompinto/kubesh
Author: João Pinto
Author-email: joao.pinto@vshn.ch
License: BSD-3
Platform: UNKNOWN
Requires-Dist: PyYAML
Requires-Dist: click
Requires-Dist: kubernetes
Requires-Dist: prompt-toolkit
Requires-Dist: pygments
Requires-Dist: tabulate
